{
  "hero": "https://storage.googleapis.com/haru2026-8abb8.firebasestorage.app/landing/hero.png",
  "feature_record": "https://storage.googleapis.com/haru2026-8abb8.firebasestorage.app/landing/feature_record.png",
  "feature_sayu": "https://storage.googleapis.com/haru2026-8abb8.firebasestorage.app/landing/feature_sayu.png",
  "feature_stats": "https://storage.googleapis.com/haru2026-8abb8.firebasestorage.app/landing/feature_stats.png",
  "sayu_premium": "https://storage.googleapis.com/haru2026-8abb8.firebasestorage.app/landing/sayu_premium.png"
}